kirznerSerializer/__init__.py
kirznerSerializer/base_serializer.py
kirznerSerializer/constants.py
kirznerSerializer/json_serializer.py
kirznerSerializer/xml_serializer.py
kirzner_serializer-0.0.3.dist-info/METADATA
kirzner_serializer-0.0.3.dist-info/WHEEL
kirzner_serializer-0.0.3.dist-info/top_level.txt
kirzner_serializer-0.0.3.dist-info/RECORD
