Metadata-Version: 2.1
Name: kirzner-serializer
Version: 0.0.3
Summary: Module for json and xml serialization
Author: Nastya Kirzner
Author-email: kirznernasta@gmail.com
License: MIT
Classifier: Intended Audience :: Developers
Classifier: License :: OSI Approved :: MIT License
Classifier: Programming Language :: Python :: 3.10
Classifier: Operating System :: OS Independent
Requires-Dist: regex
